parquet2lance-0.5.0.dist-info/METADATA
parquet2lance-0.5.0.dist-info/WHEEL
parquet2lance-0.5.0.dist-info/licenses/LICENSE
parquet2lance/__init__.py
parquet2lance/parquet2lance.cpython-312-darwin.so
parquet2lance-0.5.0.dist-info/RECORD
