Metadata-Version: 2.3
Name: parquet2lance
Version: 0.5.0
Classifier: Programming Language :: Rust
Classifier: Programming Language :: Python :: Implementation :: CPython
License-File: LICENSE
Summary: The Python wrapper for the Rust parquet2lance
Keywords: arrow,lance,parquet
Requires-Python: >=3.12
Project-URL: Source Code, https://github.com/haoxins/parquet2lance
